conviertlo/__init__.py
conviertlo/__main__.py
conviertlo/app.py
conviertlo/models/__init__.py
conviertlo/resources/__init__.py
conviertlo/resources/themes.py
conviertlo/screens/__init__.py
conviertlo/screens/file_browser_screen.py
conviertlo/screens/instruction_screen.py
conviertlo/screens/welcome_screen.py
conviertlo/services/__init__.py
conviertlo/services/copilot_service.py
conviertlo/widgets/__init__.py
conviertlo/widgets/vim_textarea.py
conviertlo-0.2.0.dist-info/METADATA
conviertlo-0.2.0.dist-info/WHEEL
conviertlo-0.2.0.dist-info/entry_points.txt
conviertlo-0.2.0.dist-info/top_level.txt
conviertlo-0.2.0.dist-info/RECORD
