Metadata-Version: 2.4
Name: conviertlo
Version: 0.2.0
Summary: A TUI tool for converting/compressing media files using FFMPEG and GitHub Copilot
Author-email: Ricardo <ricardoguzman444@gmail.com>
License: MIT
Keywords: ffmpeg,media,conversion,tui,cli
Requires-Python: >=3.10
Requires-Dist: textual>=0.47.0
Requires-Dist: rich>=13.0.0
Requires-Dist: pyyaml>=6.0
Requires-Dist: github-copilot-sdk>=0.1.0
Provides-Extra: dev
Requires-Dist: pytest>=7.0.0; extra == "dev"
Requires-Dist: black>=23.0.0; extra == "dev"
Requires-Dist: isort>=5.0.0; extra == "dev"
Requires-Dist: mypy>=1.0.0; extra == "dev"
